ben_sci_tools/__init__.py
ben_sci_tools/benterpolation.py
ben_sci_tools/colors.py
ben_sci_tools/elements.py
ben_sci_tools/halt_tools.py
ben_sci_tools/input_file_maker.py
ben_sci_tools/kinetics.py
ben_sci_tools/orca_scrapers.py
ben_sci_tools/process_data.py
ben_sci_tools/quick_calc_tools.py
ben_sci_tools-1.2.0.dist-info/METADATA
ben_sci_tools-1.2.0.dist-info/WHEEL
ben_sci_tools-1.2.0.dist-info/top_level.txt
ben_sci_tools-1.2.0.dist-info/RECORD
