Metadata-Version: 2.4
Name: ben_sci_tools
Version: 1.2.0
Summary: useful python tools that I use to streamline my work.
Author: Ben Payton
Project-URL: Documentation, https://github.com/Ben-Payton/ben_sci_tools/blob/main/README.md
Project-URL: Source, https://github.com/Ben-Payton/ben_sci_tools
Requires-Dist: numpy
Requires-Dist: pandas
Requires-Dist: matplotlib
Dynamic: author
Dynamic: description
Dynamic: description-content-type
Dynamic: project-url
Dynamic: requires-dist
Dynamic: summary
